README.rst
_description.org
lh-agpl3-LICENSE.txt
pyproject.toml
setup.py
bin/facter-assemble.cs
bin/facter-cbs-is-np-sysd.cs
bin/facter-roInv.cs
bin/facter-roPerf-sysd.cs
bin/facter-roPerf.cs
bin/facter-sbom.cs
bin/facter-svc.cs
bin/facter.cs
bisos/__init__.py
bisos.facter.egg-info/PKG-INFO
bisos.facter.egg-info/SOURCES.txt
bisos.facter.egg-info/dependency_links.txt
bisos.facter.egg-info/not-zip-safe
bisos.facter.egg-info/requires.txt
bisos.facter.egg-info/top_level.txt
bisos/facter/__init__.py
bisos/facter/facter.py
bisos/facter/facterCmdbSummary.py
bisos/facter/facterPerfSysd.py
bisos/facter/facterPy6-provenance.py
bisos/facter/facter_conv.py
bisos/facter/facter_csu.py