Metadata-Version: 2.2
Name: bisos.facter
Version: 1.32
Summary: bisos.facter:  Adoption and adaptation of facter to Python and as Command-Services
Author: Mohsen Banan
Author-email: libre@mohsen.1.banan.byname.net
Maintainer: Mohsen Banan
Maintainer-email: libre@mohsen.1.banan.byname.net
License: AGPL
Classifier: Development Status :: 5 - Production/Stable
Classifier: Intended Audience :: Developers
Classifier: License :: OSI Approved :: GNU Affero General Public License v3
Classifier: Operating System :: POSIX
Classifier: Programming Language :: Python
Classifier: Topic :: Software Development :: Libraries
Classifier: Topic :: Software Development :: Libraries :: Python Modules
Requires-Dist: bisos
Requires-Dist: bisos.b
Requires-Dist: bisos.banna
Requires-Dist: bisos.basics
Requires-Dist: bisos.capability
Requires-Dist: bisos.common
Requires-Dist: bisos.csPlayer
Requires-Dist: bisos.debian
Requires-Dist: bisos.sbom
Requires-Dist: setuptools==75.8.0
Requires-Dist: wheel==0.38.4
Dynamic: author
Dynamic: author-email
Dynamic: classifier
Dynamic: description
Dynamic: license
Dynamic: maintainer
Dynamic: maintainer-email
Dynamic: requires-dist
Dynamic: summary
